yandex_weather_api/__init__.py
yandex_weather_api/cli.py
yandex_weather_api/types.py
yandex_weather_api-0.2.4.dist-info/METADATA
yandex_weather_api-0.2.4.dist-info/RECORD
yandex_weather_api-0.2.4.dist-info/WHEEL
yandex_weather_api-0.2.4.dist-info/top_level.txt
