Metadata-Version: 1.1
Name: yandex-weather-api
Version: 0.2.4
Summary: Yandex Weather API python module
Home-page: https://github.com/ASMfreaK/yandex_weather_api
Author: Pavel Pletenev
Author-email: cpp.create@gmail.com
License: GPLv3
Platform: any
Classifier: Programming Language :: Python
Classifier: Programming Language :: Python :: 3
Classifier: Programming Language :: Python :: 3.5
Classifier: Programming Language :: Python :: 3.6
Classifier: Programming Language :: Python :: 3.7
Classifier: Programming Language :: Python :: Implementation :: CPython
Classifier: Development Status :: 4 - Beta
Classifier: Natural Language :: English
Classifier: Intended Audience :: Developers
Classifier: License :: OSI Approved :: MIT License
Classifier: Topic :: Software Development :: Libraries :: Python Modules
Classifier: Topic :: Utilities
Classifier: Topic :: Software Development
Classifier: Topic :: Software Development :: Libraries :: Python Modules
